{"id":"579bf1a7f9b869a437e368f3","name":"테스트 보드","desc":"","descData":null,"closed":false,"idOrganization":null,"invited":false,"pinned":false,"starred":false,"url":"https://trello.com/b/ph8C1wu0/-","prefs":{"permissionLevel":"private","voting":"disabled","comments":"members","invitations":"members","selfJoin":false,"cardCovers":true,"cardAging":"regular","calendarFeedEnabled":false,"background":"blue","backgroundImage":null,"backgroundImageScaled":null,"backgroundTile":false,"backgroundBrightness":"dark","backgroundColor":"#0079BF","canBePublic":true,"canBeOrg":true,"canBePrivate":true,"canInvite":true},"invitations":[],"memberships":[{"id":"579bf1a7f9b869a437e368f4","idMember":"56669dfd88a0d8eaccdd1d55","memberType":"admin","unconfirmed":false,"deactivated":false}],"shortLink":"ph8C1wu0","subscribed":false,"labelNames":{"green":"","yellow":"","orange":"","red":"","purple":"","blue":"","sky":"","lime":"","pink":"","black":""},"powerUps":[],"dateLastActivity":"2016-07-30T00:22:21.073Z","dateLastView":"2016-07-30T00:22:21.094Z","shortUrl":"https://trello.com/b/ph8C1wu0","idTags":[],"labels":[{"id":"579bf1a784e677fd36b91bef","idBoard":"579bf1a7f9b869a437e368f3","name":"","color":"green","uses":0},{"id":"579bf1a784e677fd36b91bf0","idBoard":"579bf1a7f9b869a437e368f3","name":"","color":"yellow","uses":0},{"id":"579bf1a784e677fd36b91bf1","idBoard":"579bf1a7f9b869a437e368f3","name":"","color":"orange","uses":0},{"id":"579bf1a784e677fd36b91bf2","idBoard":"579bf1a7f9b869a437e368f3","name":"","color":"red","uses":0},{"id":"579bf1a784e677fd36b91bf3","idBoard":"579bf1a7f9b869a437e368f3","name":"","color":"blue","uses":0},{"id":"579bf1a784e677fd36b91bf4","idBoard":"579bf1a7f9b869a437e368f3","name":"","color":"purple","uses":0}],"cards":[{"id":"579bf1d454ef6eaacd169ffe","checkItemStates":null,"closed":false,"dateLastActivity":"2016-07-30T00:22:21.073Z","desc":"카드 내용입니다.","descData":{"emoji":{}},"idBoard":"579bf1a7f9b869a437e368f3","idList":"579bf1c389e28c502683b8e0","idMembersVoted":[],"idShort":1,"idAttachmentCover":"","manualCoverAttachment":true,"idLabels":[],"name":"테스트 카드","pos":65535,"shortLink":"65PGlddn","badges":{"votes":0,"viewingMemberVoted":false,"subscribed":false,"fogbugz":"","checkItems":5,"checkItemsChecked":3,"comments":2,"attachments":2,"description":true,"due":null},"due":null,"email":"kevinlee173+2lbtyrx47u3ynnsnn85+2mmthznvg63cklh0bni+208q0pwjzb@boards.trello.com","idChecklists":["579bf2f2da0956aa6c77e547","579bf3189c03a5e998df09b4"],"idMembers":[],"labels":[],"shortUrl":"https://trello.com/c/65PGlddn","subscribed":false,"url":"https://trello.com/c/65PGlddn/1--","attachments":[{"bytes":2566,"date":"2016-07-30T00:19:24.854Z","edgeColor":null,"idMember":"56669dfd88a0d8eaccdd1d55","isUpload":true,"mimeType":null,"name":"test.txt","previews":[],"url":"https://trello-attachments.s3.amazonaws.com/579bf1a7f9b869a437e368f3/579bf1d454ef6eaacd169ffe/03a0f054a0da5b90d162f5bfb6029686/test.txt","id":"579bf28c376b595838e1fc21"},{"bytes":777835,"date":"2016-07-30T00:19:55.225Z","edgeColor":"#83b8de","idMember":"56669dfd88a0d8eaccdd1d55","isUpload":true,"mimeType":null,"name":"Penguins.jpg","previews":[{"width":70,"height":50,"url":"https://trello-attachments.s3.amazonaws.com/579bf1d454ef6eaacd169ffe/70x50/aea49a80a126246b7333a1450850a4c4/Penguins.jpg.png","bytes":9715,"_id":"579bf2ad6ded93167c80372d","scaled":false},{"width":250,"height":150,"url":"https://trello-attachments.s3.amazonaws.com/579bf1d454ef6eaacd169ffe/250x150/5cda0ed82eeff136f0aa5ac3c865a2ac/Penguins.jpg.png","bytes":71452,"_id":"579bf2ad6ded93167c80372c","scaled":false},{"width":150,"height":113,"url":"https://trello-attachments.s3.amazonaws.com/579bf1d454ef6eaacd169ffe/150x113/e0f935d166e57fd7399ca18708a961df/Penguins.jpg","bytes":4612,"_id":"579bf2ad6ded93167c80372b","scaled":true},{"width":300,"height":225,"url":"https://trello-attachments.s3.amazonaws.com/579bf1d454ef6eaacd169ffe/300x225/6d1c453f9d99a58dea7487b865c418f3/Penguins.jpg","bytes":12678,"_id":"579bf2ad6ded93167c80372a","scaled":true},{"width":600,"height":450,"url":"https://trello-attachments.s3.amazonaws.com/579bf1d454ef6eaacd169ffe/600x450/865b9e738c4ba3b47a5e674f1468c95d/Penguins.jpg","bytes":40448,"_id":"579bf2ad6ded93167c803729","scaled":true},{"width":1024,"height":768,"url":"https://trello-attachments.s3.amazonaws.com/579bf1d454ef6eaacd169ffe/1024x768/d007d7a4f449d08c9ee7f8d4d741924a/Penguins.jpg","bytes":777835,"_id":"579bf2ad6ded93167c803728","scaled":true}],"url":"https://trello-attachments.s3.amazonaws.com/579bf1d454ef6eaacd169ffe/1024x768/d007d7a4f449d08c9ee7f8d4d741924a/Penguins.jpg","id":"579bf2ab6ded93167c803725"}]}],"members":[{"id":"56669dfd88a0d8eaccdd1d55","avatarHash":"24abe3f14d4b62b3dec7224fa812f361","bio":"","bioData":null,"confirmed":true,"fullName":"Kevin Lee","idPremOrgsAdmin":[],"initials":"KL","memberType":"normal","products":[37],"status":"disconnected","url":"https://trello.com/kevinlee173","username":"kevinlee173"}],"lists":[{"id":"579bf1c389e28c502683b8e0","name":"테스트 리스트","closed":false,"idBoard":"579bf1a7f9b869a437e368f3","pos":65535,"subscribed":false}],"checklists":[{"id":"579bf2f2da0956aa6c77e547","name":"체크 리스트1","idBoard":"579bf1a7f9b869a437e368f3","idCard":"579bf1d454ef6eaacd169ffe","pos":16384,"checkItems":[{"state":"complete","idChecklist":"579bf2f2da0956aa6c77e547","id":"579bf2fd9ebadb897b5d4fc4","name":"할일1-1","nameData":{"emoji":{}},"pos":17211},{"state":"complete","idChecklist":"579bf2f2da0956aa6c77e547","id":"579bf300c1cf2ed142fb86da","name":"할일1-2","nameData":{"emoji":{}},"pos":34604},{"state":"incomplete","idChecklist":"579bf2f2da0956aa6c77e547","id":"579bf30bcfe82983808b6b61","name":"할일1-3","nameData":{"emoji":{}},"pos":51693}]},{"id":"579bf3189c03a5e998df09b4","name":"체크 리스트2","idBoard":"579bf1a7f9b869a437e368f3","idCard":"579bf1d454ef6eaacd169ffe","pos":32768,"checkItems":[{"state":"complete","idChecklist":"579bf3189c03a5e998df09b4","id":"579bf3285c19f5db435b6c8b","name":"할일2-1","nameData":null,"pos":16783},{"state":"incomplete","idChecklist":"579bf3189c03a5e998df09b4","id":"579bf32da62b7f4f809883c4","name":"할일2-2","nameData":null,"pos":34072}]}],"actions":[{"id":"579bf32e20faf9b36c099c27","idMemberCreator":"56669dfd88a0d8eaccdd1d55","data":{"checkItem":{"state":"complete","name":"할일2-1","id":"579bf3285c19f5db435b6c8b"},"checklist":{"name":"체크 리스트2","id":"579bf3189c03a5e998df09b4"},"card":{"shortLink":"65PGlddn","idShort":1,"name":"테스트 카드","id":"579bf1d454ef6eaacd169ffe"},"board":{"shortLink":"ph8C1wu0","name":"테스트 보드","id":"579bf1a7f9b869a437e368f3"}},"type":"updateCheckItemStateOnCard","date":"2016-07-30T00:22:06.926Z","memberCreator":{"id":"56669dfd88a0d8eaccdd1d55","avatarHash":"24abe3f14d4b62b3dec7224fa812f361","fullName":"Kevin Lee","initials":"KL","username":"kevinlee173"}},{"id":"579bf31d64c39f22c31fa6cd","idMemberCreator":"56669dfd88a0d8eaccdd1d55","data":{"board":{"shortLink":"ph8C1wu0","name":"테스트 보드","id":"579bf1a7f9b869a437e368f3"},"checklist":{"id":"579bf2f2da0956aa6c77e547","name":"체크 리스트1"},"old":{"name":"체크 리스트"}},"type":"updateChecklist","date":"2016-07-30T00:21:49.106Z","memberCreator":{"id":"56669dfd88a0d8eaccdd1d55","avatarHash":"24abe3f14d4b62b3dec7224fa812f361","fullName":"Kevin Lee","initials":"KL","username":"kevinlee173"}},{"id":"579bf3189c03a5e998df09b5","idMemberCreator":"56669dfd88a0d8eaccdd1d55","data":{"board":{"shortLink":"ph8C1wu0","name":"테스트 보드","id":"579bf1a7f9b869a437e368f3"},"checklist":{"name":"체크 리스트2","id":"579bf3189c03a5e998df09b4"},"card":{"shortLink":"65PGlddn","idShort":1,"name":"테스트 카드","id":"579bf1d454ef6eaacd169ffe"}},"type":"addChecklistToCard","date":"2016-07-30T00:21:44.592Z","memberCreator":{"id":"56669dfd88a0d8eaccdd1d55","avatarHash":"24abe3f14d4b62b3dec7224fa812f361","fullName":"Kevin Lee","initials":"KL","username":"kevinlee173"}},{"id":"579bf30e54786aff60a5a334","idMemberCreator":"56669dfd88a0d8eaccdd1d55","data":{"checkItem":{"state":"complete","name":"할일2","id":"579bf300c1cf2ed142fb86da"},"checklist":{"name":"체크 리스트","id":"579bf2f2da0956aa6c77e547"},"card":{"shortLink":"65PGlddn","idShort":1,"name":"테스트 카드","id":"579bf1d454ef6eaacd169ffe"},"board":{"shortLink":"ph8C1wu0","name":"테스트 보드","id":"579bf1a7f9b869a437e368f3"}},"type":"updateCheckItemStateOnCard","date":"2016-07-30T00:21:34.343Z","memberCreator":{"id":"56669dfd88a0d8eaccdd1d55","avatarHash":"24abe3f14d4b62b3dec7224fa812f361","fullName":"Kevin Lee","initials":"KL","username":"kevinlee173"}},{"id":"579bf30da62b7f4f80988314","idMemberCreator":"56669dfd88a0d8eaccdd1d55","data":{"checkItem":{"state":"complete","name":"할일1","id":"579bf2fd9ebadb897b5d4fc4"},"checklist":{"name":"체크 리스트","id":"579bf2f2da0956aa6c77e547"},"card":{"shortLink":"65PGlddn","idShort":1,"name":"테스트 카드","id":"579bf1d454ef6eaacd169ffe"},"board":{"shortLink":"ph8C1wu0","name":"테스트 보드","id":"579bf1a7f9b869a437e368f3"}},"type":"updateCheckItemStateOnCard","date":"2016-07-30T00:21:33.889Z","memberCreator":{"id":"56669dfd88a0d8eaccdd1d55","avatarHash":"24abe3f14d4b62b3dec7224fa812f361","fullName":"Kevin Lee","initials":"KL","username":"kevinlee173"}},{"id":"579bf2f2da0956aa6c77e548","idMemberCreator":"56669dfd88a0d8eaccdd1d55","data":{"board":{"shortLink":"ph8C1wu0","name":"테스트 보드","id":"579bf1a7f9b869a437e368f3"},"checklist":{"name":"체크 리스트","id":"579bf2f2da0956aa6c77e547"},"card":{"shortLink":"65PGlddn","idShort":1,"name":"테스트 카드","id":"579bf1d454ef6eaacd169ffe"}},"type":"addChecklistToCard","date":"2016-07-30T00:21:06.317Z","memberCreator":{"id":"56669dfd88a0d8eaccdd1d55","avatarHash":"24abe3f14d4b62b3dec7224fa812f361","fullName":"Kevin Lee","initials":"KL","username":"kevinlee173"}},{"id":"579bf2b96df3929b37b276de","idMemberCreator":"56669dfd88a0d8eaccdd1d55","data":{"list":{"name":"테스트 리스트","id":"579bf1c389e28c502683b8e0"},"board":{"shortLink":"ph8C1wu0","name":"테스트 보드","id":"579bf1a7f9b869a437e368f3"},"card":{"shortLink":"65PGlddn","idShort":1,"name":"테스트 카드","id":"579bf1d454ef6eaacd169ffe","idAttachmentCover":""},"old":{"idAttachmentCover":"579bf2ab6ded93167c803725"}},"type":"updateCard","date":"2016-07-30T00:20:09.738Z","memberCreator":{"id":"56669dfd88a0d8eaccdd1d55","avatarHash":"24abe3f14d4b62b3dec7224fa812f361","fullName":"Kevin Lee","initials":"KL","username":"kevinlee173"}},{"id":"579bf2ad6ded93167c80372e","idMemberCreator":"56669dfd88a0d8eaccdd1d55","data":{"board":{"shortLink":"ph8C1wu0","name":"테스트 보드","id":"579bf1a7f9b869a437e368f3"},"card":{"shortLink":"65PGlddn","idShort":1,"name":"테스트 카드","id":"579bf1d454ef6eaacd169ffe"},"attachment":{"previewUrl2x":"https://trello-attachments.s3.amazonaws.com/579bf1d454ef6eaacd169ffe/1024x768/d007d7a4f449d08c9ee7f8d4d741924a/Penguins.jpg","previewUrl":"https://trello-attachments.s3.amazonaws.com/579bf1d454ef6eaacd169ffe/600x450/865b9e738c4ba3b47a5e674f1468c95d/Penguins.jpg","url":"https://trello-attachments.s3.amazonaws.com/579bf1d454ef6eaacd169ffe/1024x768/d007d7a4f449d08c9ee7f8d4d741924a/Penguins.jpg","name":"Penguins.jpg","id":"579bf2ab6ded93167c803725"}},"type":"addAttachmentToCard","date":"2016-07-30T00:19:57.230Z","memberCreator":{"id":"56669dfd88a0d8eaccdd1d55","avatarHash":"24abe3f14d4b62b3dec7224fa812f361","fullName":"Kevin Lee","initials":"KL","username":"kevinlee173"}},{"id":"579bf28c376b595838e1fc22","idMemberCreator":"56669dfd88a0d8eaccdd1d55","data":{"board":{"shortLink":"ph8C1wu0","name":"테스트 보드","id":"579bf1a7f9b869a437e368f3"},"card":{"shortLink":"65PGlddn","idShort":1,"name":"테스트 카드","id":"579bf1d454ef6eaacd169ffe"},"attachment":{"url":"https://trello-attachments.s3.amazonaws.com/579bf1a7f9b869a437e368f3/579bf1d454ef6eaacd169ffe/03a0f054a0da5b90d162f5bfb6029686/test.txt","name":"test.txt","id":"579bf28c376b595838e1fc21"}},"type":"addAttachmentToCard","date":"2016-07-30T00:19:24.956Z","memberCreator":{"id":"56669dfd88a0d8eaccdd1d55","avatarHash":"24abe3f14d4b62b3dec7224fa812f361","fullName":"Kevin Lee","initials":"KL","username":"kevinlee173"}},{"id":"579bf1fb346678e1cda36fa3","idMemberCreator":"56669dfd88a0d8eaccdd1d55","data":{"list":{"name":"테스트 리스트","id":"579bf1c389e28c502683b8e0"},"board":{"shortLink":"ph8C1wu0","name":"테스트 보드","id":"579bf1a7f9b869a437e368f3"},"card":{"shortLink":"65PGlddn","idShort":1,"name":"테스트 카드","id":"579bf1d454ef6eaacd169ffe"},"text":"코멘트2"},"type":"commentCard","date":"2016-07-30T00:16:59.554Z","memberCreator":{"id":"56669dfd88a0d8eaccdd1d55","avatarHash":"24abe3f14d4b62b3dec7224fa812f361","fullName":"Kevin Lee","initials":"KL","username":"kevinlee173"}},{"id":"579bf1f7ad815fb0c5695698","idMemberCreator":"56669dfd88a0d8eaccdd1d55","data":{"list":{"name":"테스트 리스트","id":"579bf1c389e28c502683b8e0"},"board":{"shortLink":"ph8C1wu0","name":"테스트 보드","id":"579bf1a7f9b869a437e368f3"},"card":{"shortLink":"65PGlddn","idShort":1,"name":"테스트 카드","id":"579bf1d454ef6eaacd169ffe"},"text":"코멘트1"},"type":"commentCard","date":"2016-07-30T00:16:55.591Z","memberCreator":{"id":"56669dfd88a0d8eaccdd1d55","avatarHash":"24abe3f14d4b62b3dec7224fa812f361","fullName":"Kevin Lee","initials":"KL","username":"kevinlee173"}},{"id":"579bf1eff0a6cde2c5ccdb68","idMemberCreator":"56669dfd88a0d8eaccdd1d55","data":{"list":{"name":"테스트 리스트","id":"579bf1c389e28c502683b8e0"},"board":{"shortLink":"ph8C1wu0","name":"테스트 보드","id":"579bf1a7f9b869a437e368f3"},"card":{"shortLink":"65PGlddn","idShort":1,"name":"테스트 카드","id":"579bf1d454ef6eaacd169ffe","desc":"카드 내용입니다."},"old":{"desc":""}},"type":"updateCard","date":"2016-07-30T00:16:47.339Z","memberCreator":{"id":"56669dfd88a0d8eaccdd1d55","avatarHash":"24abe3f14d4b62b3dec7224fa812f361","fullName":"Kevin Lee","initials":"KL","username":"kevinlee173"}},{"id":"579bf1d920dc4aa026941ef8","idMemberCreator":"56669dfd88a0d8eaccdd1d55","data":{"board":{"shortLink":"ph8C1wu0","name":"테스트 보드","id":"579bf1a7f9b869a437e368f3"},"list":{"id":"579bf1c389e28c502683b8e0","name":"테스트 리스트"},"old":{"name":"테스트 리스트 in 테스트 보드"}},"type":"updateList","date":"2016-07-30T00:16:25.526Z","memberCreator":{"id":"56669dfd88a0d8eaccdd1d55","avatarHash":"24abe3f14d4b62b3dec7224fa812f361","fullName":"Kevin Lee","initials":"KL","username":"kevinlee173"}},{"id":"579bf1d454ef6eaacd169fff","idMemberCreator":"56669dfd88a0d8eaccdd1d55","data":{"board":{"shortLink":"ph8C1wu0","name":"테스트 보드","id":"579bf1a7f9b869a437e368f3"},"list":{"name":"테스트 리스트 in 테스트 보드","id":"579bf1c389e28c502683b8e0"},"card":{"shortLink":"65PGlddn","idShort":1,"name":"테스트 카드","id":"579bf1d454ef6eaacd169ffe"}},"type":"createCard","date":"2016-07-30T00:16:20.462Z","memberCreator":{"id":"56669dfd88a0d8eaccdd1d55","avatarHash":"24abe3f14d4b62b3dec7224fa812f361","fullName":"Kevin Lee","initials":"KL","username":"kevinlee173"}},{"id":"579bf1c389e28c502683b8e1","idMemberCreator":"56669dfd88a0d8eaccdd1d55","data":{"board":{"shortLink":"ph8C1wu0","name":"테스트 보드","id":"579bf1a7f9b869a437e368f3"},"list":{"name":"테스트 리스트 in 테스트 보드","id":"579bf1c389e28c502683b8e0"}},"type":"createList","date":"2016-07-30T00:16:03.865Z","memberCreator":{"id":"56669dfd88a0d8eaccdd1d55","avatarHash":"24abe3f14d4b62b3dec7224fa812f361","fullName":"Kevin Lee","initials":"KL","username":"kevinlee173"}},{"id":"579bf1a7f9b869a437e368f5","idMemberCreator":"56669dfd88a0d8eaccdd1d55","data":{"board":{"shortLink":"ph8C1wu0","name":"테스트 보드","id":"579bf1a7f9b869a437e368f3"}},"type":"createBoard","date":"2016-07-30T00:15:35.140Z","memberCreator":{"id":"56669dfd88a0d8eaccdd1d55","avatarHash":"24abe3f14d4b62b3dec7224fa812f361","fullName":"Kevin Lee","initials":"KL","username":"kevinlee173"}}]}